parsinorm/__init__.py
parsinorm/abbreviation.py
parsinorm/date_time_to_text.py
parsinorm/general_normalization.py
parsinorm/mail_url_cleaner.py
parsinorm/special_numbers.py
parsinorm/telephone_number.py
parsinorm/tokenizer.py
parsinorm/tts_normalization.py
parsinorm-0.0.3.dist-info/LICENSE
parsinorm-0.0.3.dist-info/METADATA
parsinorm-0.0.3.dist-info/WHEEL
parsinorm-0.0.3.dist-info/top_level.txt
parsinorm-0.0.3.dist-info/RECORD
