Metadata-Version: 2.1
Name: parsinorm
Version: 0.0.3
Summary: Persain Text Pre-Proceesing Tool
Home-page: https://github.com/haraai/ParsiNorm
Author: HaraAi
Author-email: info@hara.ai
License: UNKNOWN
Platform: UNKNOWN
Classifier: Programming Language :: Python :: 3
Classifier: License :: OSI Approved :: MIT License
Classifier: Operating System :: OS Independent
Requires-Dist: num2fawords (==1.1)
Requires-Dist: persian-tools (==0.0.10)
Requires-Dist: urlextract (==1.4.0)
Requires-Dist: nltk (==3.3)
Requires-Dist: hazm (==0.7.0)
